{
  "id": "beer_home_hero",
  "title": "Beer: Hero",
  "category": "Beer / Картинки",
  "version": "1.0.0",
  "type": "htmlEmbed",
  "defaults": {
    "img": "../app/blocks/_beer_shared/img/beer_hero.jpg",
    "alt": "Beer"
  },
  "schema": [
    {
      "key": "img",
      "label": "Картинка",
      "ui": "image"
    },
    {
      "key": "alt",
      "label": "Alt",
      "ui": "text"
    }
  ],
  "assets": {
    "css": [
      "../_beer_shared/beer.scoped.css"
    ]
  },
  "tags": [
    "home",
    "beer",
    "all"
  ]
}